{
    "scene_info": {
        "name": "scene_0013"
    },
    "frames": [
        {
            "frame_index": 0,
            "image_name": "scene_0013_000.jpg",
            "metrics": {
                "ADE_1s": 0.10252811003152545,
                "ADE_2s": 0.19063588827251443,
                "ADE_3s": 0.9721259391212673,
                "ADE_avg": 0.4217633124751024,
                "FDE": 1.2381156737338919,
                "missRate_2": 0.0
            },
            "inference": {
                "actions": "[(7.503, 0), (8.503, 0), (9.503, 0), (10.503, 0), (11.503, 0), (12.503, 0)]"
            }
        },
        {
            "frame_index": 2,
            "image_name": "scene_0013_002.jpg",
            "metrics": {
                "ADE_1s": 0.08756659728514668,
                "ADE_2s": 0.8598775444472068,
                "ADE_3s": 2.797564432326011,
                "ADE_avg": 1.248336191352788,
                "FDE": 3.3733701129162834,
                "missRate_2": 1.0
            },
            "inference": {
                "actions": "[(7.894493734000504, 0.0), (8.644493734000504, 0.0), (9.394493734000504, 0.0), (10.144493734000504, 0.0), (10.894493734000504, 0.0), (11.644493734000504, 0.0)]"
            }
        },
        {
            "frame_index": 4,
            "image_name": "scene_0013_004.jpg",
            "metrics": {
                "ADE_1s": 0.06837439051219295,
                "ADE_2s": 0.7173590032061207,
                "ADE_3s": 2.532104143944488,
                "ADE_avg": 1.1059458458876004,
                "FDE": 3.0631897255763554,
                "missRate_2": 1.0
            },
            "inference": {
                "actions": "[(8.480265571478903, 0.00), (9.230265571478903, 0.00), (9.980265571478903, 0.00), (10.730265571478903, 0.00), (11.480265571478903, 0.00), (12.230265571478903, 0.00)]"
            }
        },
        {
            "frame_index": 6,
            "image_name": "scene_0013_006.jpg",
            "metrics": {
                "ADE_1s": 0.4255723335705035,
                "ADE_2s": 0.6577678138804516,
                "ADE_3s": 0.6398237174199455,
                "ADE_avg": 0.5743879549569669,
                "FDE": 0.6458419389474009,
                "missRate_2": 0.0
            },
            "inference": {
                "actions": "[(9.306, 0.0), (10.406, 0.0), (11.506, 0.0), (12.606, 0.0), (13.706, 0.0), (14.806, 0.0)]"
            }
        },
        {
            "frame_index": 8,
            "image_name": "scene_0013_008.jpg",
            "metrics": {
                "ADE_1s": 0.27732663217660647,
                "ADE_2s": 0.25983734613598547,
                "ADE_3s": 0.8881461346687665,
                "ADE_avg": 0.47510337099378613,
                "FDE": 1.1475967415800774,
                "missRate_2": 0.0
            },
            "inference": {
                "actions": "[(9.6187, 0.002), (10.6187, 0.002), (11.6187, 0.002), (12.6187, 0.002), (13.6187, 0.002), (14.6187, 0.002)]"
            }
        },
        {
            "frame_index": 10,
            "image_name": "scene_0013_010.jpg",
            "metrics": {
                "ADE_1s": 0.19770253397282797,
                "ADE_2s": 1.7012897630552688,
                "ADE_3s": 4.336516707410494,
                "ADE_avg": 2.0785030014795307,
                "FDE": 5.135603589914196,
                "missRate_2": 1.0
            },
            "inference": {
                "actions": "[(9.647, 0.0), (10.231, 0.0), (10.814, 0.0), (11.397, 0.0), (11.981, 0.0), (12.564, 0.0)]"
            }
        },
        {
            "frame_index": 12,
            "image_name": "scene_0013_012.jpg",
            "metrics": {
                "ADE_1s": 0.1470547978785557,
                "ADE_2s": 1.105553641378818,
                "ADE_3s": 2.89397162400741,
                "ADE_avg": 1.3821933544215945,
                "FDE": 3.4282747474204047,
                "missRate_2": 1.0
            },
            "inference": {
                "actions": "[(10.276, 0.0), (11.026, 0.0), (11.776, 0.0), (12.526, 0.0), (13.276, 0.0), (14.026, 0.0)]"
            }
        },
        {
            "frame_index": 14,
            "image_name": "scene_0013_014.jpg",
            "metrics": {
                "ADE_1s": 1.0684339115027484,
                "ADE_2s": 4.614087437060716,
                "ADE_3s": 10.363634759410008,
                "ADE_avg": 5.348718702657824,
                "FDE": 12.062941128706541,
                "missRate_2": 1.0
            },
            "inference": {
                "actions": "[(9.75, 0.001), (9.75, 0.001), (9.75, 0.001), (9.75, 0.001), (9.75, 0.001), (9.75, 0.001)]"
            }
        },
        {
            "frame_index": 16,
            "image_name": "scene_0013_016.jpg",
            "metrics": {
                "ADE_1s": 0.37039821789127914,
                "ADE_2s": 1.0496617807668847,
                "ADE_3s": 2.162516030314732,
                "ADE_avg": 1.194192009657632,
                "FDE": 2.5175684045313442,
                "missRate_2": 1.0
            },
            "inference": {
                "actions": "[(11.8245, 0.0), (13.1245, 0.0), (14.4245, 0.0), (15.7245, 0.0), (17.0245, 0.0), (18.3245, 0.0)]"
            }
        },
        {
            "frame_index": 18,
            "image_name": "scene_0013_018.jpg",
            "metrics": {
                "ADE_1s": 0.10836533667229306,
                "ADE_2s": 0.8363119314892893,
                "ADE_3s": 2.228317821375343,
                "ADE_avg": 1.0576650298456416,
                "FDE": 2.622838087707579,
                "missRate_2": 1.0
            },
            "inference": {
                "actions": "[(11.929, 0.0), (12.679, 0.0), (13.429, 0.0), (14.179, 0.0), (14.929, 0.0), (15.679, 0.0)]"
            }
        },
        {
            "frame_index": 20,
            "image_name": "scene_0013_020.jpg",
            "metrics": {
                "ADE_1s": 0.1279388420486569,
                "ADE_2s": 1.0399402022591369,
                "ADE_3s": 2.740657026445371,
                "ADE_avg": 1.3028453569177216,
                "FDE": 3.2282282384391316,
                "missRate_2": 1.0
            },
            "inference": {
                "actions": "[(12.4021, 0.0), (13.0521, 0.0), (13.7021, 0.0), (14.3521, 0.0), (15.0021, 0.0), (15.6521, 0.0)]"
            }
        },
        {
            "frame_index": 22,
            "image_name": "scene_0013_022.jpg",
            "metrics": {
                "ADE_1s": 0.526439961240557,
                "ADE_2s": 1.4824011476747567,
                "ADE_3s": 2.9352355076272065,
                "ADE_avg": 1.648025538847507,
                "FDE": 3.39219275636606,
                "missRate_2": 1.0
            },
            "inference": {
                "actions": "[(13.52, 0.0), (14.77, 0.0), (16.02, 0.0), (17.27, 0.0), (18.52, 0.0), (19.77, 0.0)]"
            }
        },
        {
            "frame_index": 24,
            "image_name": "scene_0013_024.jpg",
            "metrics": {
                "ADE_1s": 0.3101980457996657,
                "ADE_2s": 0.5715677011750246,
                "ADE_3s": 0.9085739464045353,
                "ADE_avg": 0.5967798977930752,
                "FDE": 1.0284389317928613,
                "missRate_2": 0.0
            },
            "inference": {
                "actions": "[(13.757, 0.0), (14.757, 0.0), (15.757, 0.0), (16.757, 0.0), (17.757, 0.0), (18.757, 0.0)]"
            }
        },
        {
            "frame_index": 26,
            "image_name": "scene_0013_026.jpg",
            "metrics": {
                "ADE_1s": 0.079920342797778,
                "ADE_2s": 0.36254985405512075,
                "ADE_3s": 1.1579517790712124,
                "ADE_avg": 0.5334739919747037,
                "FDE": 1.3803500398182649,
                "missRate_2": 0.0
            },
            "inference": {
                "actions": "[(13.9694, 0.0), (14.7194, 0.0), (15.4694, 0.0), (16.2194, 0.0), (16.9694, 0.0), (17.7194, 0.0)]"
            }
        },
        {
            "frame_index": 28,
            "image_name": "scene_0013_028.jpg",
            "metrics": {
                "ADE_1s": 0.38417808956006877,
                "ADE_2s": 0.8338283792844114,
                "ADE_3s": 1.5707617229563926,
                "ADE_avg": 0.9295893972669577,
                "FDE": 1.8054515355679874,
                "missRate_2": 0.0
            },
            "inference": {
                "actions": "[(14.70061172857433, 0.0), (15.73561172857433, 0.0), (16.77061172857433, 0.0), (17.80561172857433, 0.0), (18.84061172857433, 0.0), (19.87561172857433, 0.0)]"
            }
        },
        {
            "frame_index": 30,
            "image_name": "scene_0013_030.jpg",
            "metrics": {
                "ADE_1s": 0.35052195220329846,
                "ADE_2s": 0.7480393219476043,
                "ADE_3s": 1.4105540526550342,
                "ADE_avg": 0.836371775601979,
                "FDE": 1.620286666067688,
                "missRate_2": 0.0
            },
            "inference": {
                "actions": "[(15.100311626377398, 0.0), (16.100311626377398, 0.0), (17.100311626377398, 0.0), (18.100311626377398, 0.0), (19.100311626377398, 0.0), (20.100311626377398, 0.0)]"
            }
        },
        {
            "frame_index": 32,
            "image_name": "scene_0013_032.jpg",
            "metrics": {
                "ADE_1s": 0.5384842140540945,
                "ADE_2s": 2.4693235558868296,
                "ADE_3s": 5.590697466861086,
                "ADE_avg": 2.8661684122673368,
                "FDE": 6.504607561848309,
                "missRate_2": 1.0
            },
            "inference": {
                "actions": "[(14.63633681944073, 0.0), (14.88633681944073, 0.0), (15.13633681944073, 0.0), (15.38633681944073, 0.0), (15.63633681944073, 0.0), (15.88633681944073, 0.0)]"
            }
        },
        {
            "frame_index": 34,
            "image_name": "scene_0013_034.jpg",
            "metrics": {
                "ADE_1s": 0.6914842075474673,
                "ADE_2s": 3.1563892757350622,
                "ADE_3s": 7.276578975605626,
                "ADE_avg": 3.708150819629385,
                "FDE": 8.493982199280843,
                "missRate_2": 1.0
            },
            "inference": {
                "actions": "[(14.955100581872511, 0.0), (14.955100581872511, 0.0), (14.955100581872511, 0.0), (14.955100581872511, 0.0), (14.955100581872511, 0.0), (14.955100581872511, 0.0)]"
            }
        },
        {
            "frame_index": 36,
            "image_name": "scene_0013_036.jpg",
            "metrics": {
                "ADE_1s": 0.3683344457388957,
                "ADE_2s": 1.0395807871896063,
                "ADE_3s": 2.082641108255243,
                "ADE_avg": 1.163518780394582,
                "FDE": 2.407693431057874,
                "missRate_2": 1.0
            },
            "inference": {
                "actions": "[(16.43604606529148, 0.0), (17.43604606529148, 0.0), (18.43604606529148, 0.0), (19.43604606529148, 0.0), (20.43604606529148, 0.0), (21.43604606529148, 0.0)]"
            }
        },
        {
            "frame_index": 38,
            "image_name": "scene_0013_038.jpg",
            "metrics": {
                "ADE_1s": 0.4053269975118682,
                "ADE_2s": 1.1641491483503255,
                "ADE_3s": 2.3291331322326108,
                "ADE_avg": 1.2995364260316016,
                "FDE": 2.671104702601053,
                "missRate_2": 1.0
            },
            "inference": {
                "actions": "[(16.8625, 0.0), (17.8625, 0.0), (18.8625, 0.0), (19.8625, 0.0), (20.8625, 0.0), (21.8625, 0.0)]"
            }
        },
        {
            "frame_index": 40,
            "image_name": "scene_0013_040.jpg",
            "metrics": {
                "ADE_1s": 0.30382156582577147,
                "ADE_2s": 0.7466143113138684,
                "ADE_3s": 1.3712264783038344,
                "ADE_avg": 0.8072207851478247,
                "FDE": 1.5442418700121314,
                "missRate_2": 0.0
            },
            "inference": {
                "actions": "[(17.130555358954084, 0.0), (18.005555358954084, 0.0), (18.880555358954084, 0.0), (19.755555358954084, 0.0), (20.630555358954084, 0.0), (21.505555358954084, 0.0)]"
            }
        },
        {
            "frame_index": 42,
            "image_name": "scene_0013_042.jpg",
            "metrics": {
                "ADE_1s": 0.07856701030946873,
                "ADE_2s": 0.6853556449655492,
                "ADE_3s": 1.8802121822724627,
                "ADE_avg": 0.8813782791824935,
                "FDE": 2.250096968135909,
                "missRate_2": 1.0
            },
            "inference": {
                "actions": "[(17.12793, 0.0), (17.62793, 0.0), (18.12793, 0.0), (18.62793, 0.0), (19.12793, 0.0), (19.62793, 0.0)]"
            }
        },
        {
            "frame_index": 44,
            "image_name": "scene_0013_044.jpg",
            "metrics": {
                "ADE_1s": 0.20786437394657534,
                "ADE_2s": 0.3728284353355469,
                "ADE_3s": 0.4822660741909801,
                "ADE_avg": 0.35431962782436743,
                "FDE": 0.5087999750218697,
                "missRate_2": 0.0
            },
            "inference": {
                "actions": "[(17.74, 0.0), (18.49, 0.0), (19.24, 0.0), (19.99, 0.0), (20.74, 0.0), (21.49, 0.0)]"
            }
        },
        {
            "frame_index": 46,
            "image_name": "scene_0013_046.jpg",
            "metrics": {
                "ADE_1s": 0.3490642425392853,
                "ADE_2s": 0.9482055006668817,
                "ADE_3s": 1.7815602657426846,
                "ADE_avg": 1.026276669649617,
                "FDE": 2.0299102453683773,
                "missRate_2": 1.0
            },
            "inference": {
                "actions": "[(18.222, 0.0), (19.107, 0.0), (19.992, 0.0), (20.877, 0.0), (21.762, 0.0), (22.647, 0.0)]"
            }
        },
        {
            "frame_index": 48,
            "image_name": "scene_0013_048.jpg",
            "metrics": {
                "ADE_1s": 0.5060967440999978,
                "ADE_2s": 1.5942978230357652,
                "ADE_3s": 3.223514348737993,
                "ADE_avg": 1.774636305291252,
                "FDE": 3.7172142424739327,
                "missRate_2": 1.0
            },
            "inference": {
                "actions": "[(18.71567, 0.0), (19.75067, 0.0), (20.78567, 0.0), (21.82067, 0.0), (22.85567, 0.0), (23.89067, 0.0)]"
            }
        }
    ],
    "scene_metrics": {
        "ADE_avg": 1.384604033501955,
        "FDE": 3.1127175805954543,
        "missRate_2": 0.64
    }
}