{
    "scene_info": {
        "name": "scene_0032"
    },
    "frames": [
        {
            "frame_index": 0,
            "image_name": "scene_0032_000.jpg",
            "metrics": {
                "ADE_1s": 0.07217050190446574,
                "ADE_2s": 0.3361256269609693,
                "ADE_3s": 0.9215494068470254,
                "ADE_avg": 0.44328184523748676,
                "FDE": 1.0658148630868696,
                "missRate_2": 0.0
            },
            "inference": {
                "actions": "[(7.185, 0.004), (7.935, 0.004), (8.333, 0.004), (8.333, 0.004), (8.333, 0.004), (8.333, 0.004)]"
            }
        },
        {
            "frame_index": 2,
            "image_name": "scene_0032_002.jpg",
            "metrics": {
                "ADE_1s": 0.31769018666310966,
                "ADE_2s": 0.39379794827783465,
                "ADE_3s": 0.303493053569254,
                "ADE_avg": 0.33832706283673275,
                "FDE": 0.43145326619679875,
                "missRate_2": 0.0
            },
            "inference": {
                "actions": "[(7.335, 0.000), (7.585, 0.000), (7.835, 0.000), (8.085, 0.000), (8.335, 0.000), (8.585, 0.000)]"
            }
        },
        {
            "frame_index": 4,
            "image_name": "scene_0032_004.jpg",
            "metrics": {
                "ADE_1s": 0.5115097847510429,
                "ADE_2s": 2.5371774416404107,
                "ADE_3s": 6.114134539471417,
                "ADE_avg": 3.0542739219542896,
                "FDE": 7.234879991522503,
                "missRate_2": 1.0
            },
            "inference": {
                "actions": "[(8.425, 0.0), (9.175, 0.0), (9.925, 0.0), (10.675, 0.0), (11.425, 0.0), (12.175, 0.0)]"
            }
        },
        {
            "frame_index": 6,
            "image_name": "scene_0032_006.jpg",
            "metrics": {
                "ADE_1s": 0.4744511508238329,
                "ADE_2s": 2.0431193168705386,
                "ADE_3s": 4.797284367028246,
                "ADE_avg": 2.438284944907539,
                "FDE": 5.61808536373729,
                "missRate_2": 1.0
            },
            "inference": {
                "actions": "[(7.551, 0.0), (6.941, 0.0), (6.331, 0.0), (5.721, 0.0), (5.111, 0.0), (4.501, 0.0)]"
            }
        },
        {
            "frame_index": 8,
            "image_name": "scene_0032_008.jpg",
            "metrics": {
                "ADE_1s": 0.7101113223340597,
                "ADE_2s": 2.476541769769362,
                "ADE_3s": 5.471805559845288,
                "ADE_avg": 2.886152883982904,
                "FDE": 6.445854667109017,
                "missRate_2": 1.0
            },
            "inference": {
                "actions": "[(8.67, 0.0), (9.17, 0.0), (9.67, 0.0), (10.17, 0.0), (10.67, 0.0), (11.17, 0.0)]"
            }
        },
        {
            "frame_index": 10,
            "image_name": "scene_0032_010.jpg",
            "metrics": {
                "ADE_1s": 0.034311670884626194,
                "ADE_2s": 0.09381402774047533,
                "ADE_3s": 1.4255518040140394,
                "ADE_avg": 0.5178925008797136,
                "FDE": 2.140999141857894,
                "missRate_2": 1.0
            },
            "inference": {
                "actions": "[(7.9, 0.0), (7.9, 0.0), (7.9, 0.0), (7.9, 0.0), (7.9, 0.0), (7.9, 0.0)]"
            }
        },
        {
            "frame_index": 12,
            "image_name": "scene_0032_012.jpg",
            "metrics": {
                "ADE_1s": 0.1135598416011712,
                "ADE_2s": 0.324531511702798,
                "ADE_3s": 2.045011664826691,
                "ADE_avg": 0.8277010060435535,
                "FDE": 2.939079513026066,
                "missRate_2": 1.0
            },
            "inference": {
                "actions": "[(7.74, 0.0), (7.74, 0.0), (7.74, 0.0), (7.74, 0.0), (7.74, 0.0), (7.74, 0.0)]"
            }
        },
        {
            "frame_index": 14,
            "image_name": "scene_0032_014.jpg",
            "metrics": {
                "ADE_1s": 0.058164962095360206,
                "ADE_2s": 0.26736923158297166,
                "ADE_3s": 2.6905160703680067,
                "ADE_avg": 1.0053500880154462,
                "FDE": 3.8070962543618267,
                "missRate_2": 1.0
            },
            "inference": {
                "actions": "[(7.85, 0.001), (7.85, 0.001), (7.85, 0.001), (7.85, 0.001), (7.85, 0.001), (7.85, 0.001)]"
            }
        },
        {
            "frame_index": 16,
            "image_name": "scene_0032_016.jpg",
            "metrics": {
                "ADE_1s": 0.055865520496746306,
                "ADE_2s": 0.7800557503589212,
                "ADE_3s": 4.832188988019421,
                "ADE_avg": 1.8893700862916962,
                "FDE": 6.484519056980816,
                "missRate_2": 1.0
            },
            "inference": {
                "actions": "[(7.977, -0.002), (7.977, -0.004), (7.977, -0.006), (7.977, -0.008), (7.977, -0.010), (7.977, -0.010)]"
            }
        },
        {
            "frame_index": 18,
            "image_name": "scene_0032_018.jpg",
            "metrics": {
                "ADE_1s": 0.084004045775427,
                "ADE_2s": 1.1927705168706453,
                "ADE_3s": 6.181332382818247,
                "ADE_avg": 2.4860356484881065,
                "FDE": 8.09766948927054,
                "missRate_2": 1.0
            },
            "inference": {
                "actions": "[(7.969, -0.0025), (7.969, -0.0050), (7.969, -0.0075), (7.969, -0.0075), (7.969, -0.0075), (7.969, -0.0075)]"
            }
        },
        {
            "frame_index": 20,
            "image_name": "scene_0032_020.jpg",
            "metrics": {
                "ADE_1s": 0.0938762613120958,
                "ADE_2s": 1.7550164430230537,
                "ADE_3s": 8.020456934945079,
                "ADE_avg": 3.289783213093409,
                "FDE": 10.308513499607551,
                "missRate_2": 1.0
            },
            "inference": {
                "actions": "[(7.895, -0.003), (7.900, -0.007), (7.905, -0.011), (7.910, -0.015), (7.910, -0.015), (7.910, -0.015)]"
            }
        },
        {
            "frame_index": 22,
            "image_name": "scene_0032_022.jpg",
            "metrics": {
                "ADE_1s": 0.5482266410268575,
                "ADE_2s": 6.502927167704214,
                "ADE_3s": 19.677252126819564,
                "ADE_avg": 8.909468645183544,
                "FDE": 23.561272708074082,
                "missRate_2": 1.0
            },
            "inference": {
                "actions": "[(7.9, -0.05), (7.9, -0.09), (7.9, -0.09), (7.9, -0.09), (7.9, -0.09), (7.9, -0.09)]"
            }
        },
        {
            "frame_index": 24,
            "image_name": "scene_0032_024.jpg",
            "metrics": {
                "ADE_1s": 0.2689391200087082,
                "ADE_2s": 2.953948258152864,
                "ADE_3s": 10.534886200818038,
                "ADE_avg": 4.5859245263265365,
                "FDE": 13.049323580552597,
                "missRate_2": 1.0
            },
            "inference": {
                "actions": "[(7.89, -0.001), (7.88, -0.003), (7.88, -0.005), (7.89, -0.007), (7.89, -0.008), (7.88, -0.008)]"
            }
        },
        {
            "frame_index": 26,
            "image_name": "scene_0032_026.jpg",
            "metrics": {
                "ADE_1s": 0.4000868784725096,
                "ADE_2s": 4.046996126167755,
                "ADE_3s": 13.384966563032492,
                "ADE_avg": 5.944016522557585,
                "FDE": 16.307429985281832,
                "missRate_2": 1.0
            },
            "inference": {
                "actions": "[(7.92, 0.000), (7.91, -0.010), (7.90, -0.020), (7.89, -0.025), (7.88, -0.025), (7.87, -0.025)]"
            }
        },
        {
            "frame_index": 28,
            "image_name": "scene_0032_028.jpg",
            "metrics": {
                "ADE_1s": 0.6653242966547551,
                "ADE_2s": 4.731672073349364,
                "ADE_3s": 13.731226452552539,
                "ADE_avg": 6.3760742741855525,
                "FDE": 16.353799089616636,
                "missRate_2": 1.0
            },
            "inference": {
                "actions": "[(7.94, 0.004), (7.96, 0.000), (7.98, -0.005), (8.00, -0.010), (8.02, -0.015), (8.04, -0.020)]"
            }
        },
        {
            "frame_index": 30,
            "image_name": "scene_0032_030.jpg",
            "metrics": {
                "ADE_1s": 1.0400500717678578,
                "ADE_2s": 5.958616944191483,
                "ADE_3s": 14.871919004016313,
                "ADE_avg": 7.290195339991885,
                "FDE": 17.129836483808123,
                "missRate_2": 1.0
            },
            "inference": {
                "actions": "[(7.869, 0.002), (7.885, 0.0), (7.900, 0.0), (7.900, 0.0), (7.900, 0.0), (7.900, 0.0)]"
            }
        },
        {
            "frame_index": 32,
            "image_name": "scene_0032_032.jpg",
            "metrics": {
                "ADE_1s": 1.1462617571675475,
                "ADE_2s": 6.46782654439048,
                "ADE_3s": 14.969576774411749,
                "ADE_avg": 7.527888358656592,
                "FDE": 16.950704158641663,
                "missRate_2": 1.0
            },
            "inference": {
                "actions": "[(7.76, 0.002), (7.76, 0.002), (7.76, 0.002), (7.76, 0.002), (7.76, 0.002), (7.76, 0.002)]"
            }
        },
        {
            "frame_index": 34,
            "image_name": "scene_0032_034.jpg",
            "metrics": {
                "ADE_1s": 1.031132807267279,
                "ADE_2s": 4.052337078230235,
                "ADE_3s": 7.107470822891511,
                "ADE_avg": 4.063646902796342,
                "FDE": 7.503255187111107,
                "missRate_2": 1.0
            },
            "inference": {
                "actions": "[(7.77, 0.052), (7.77, 0.052), (7.77, 0.052), (7.77, 0.052), (7.77, 0.052), (7.77, 0.052)]"
            }
        },
        {
            "frame_index": 36,
            "image_name": "scene_0032_036.jpg",
            "metrics": {
                "ADE_1s": 1.3970091484831664,
                "ADE_2s": 6.04261957226964,
                "ADE_3s": 10.929801827951106,
                "ADE_avg": 6.123143516234638,
                "FDE": 11.923669465135113,
                "missRate_2": 1.0
            },
            "inference": {
                "actions": "[(7.880623333403838, 0.031), (7.880623333403838, 0.031), (7.880623333403838, 0.031), (7.880623333403838, 0.031), (7.880623333403838, 0.031), (7.880623333403838, 0.031)]"
            }
        },
        {
            "frame_index": 38,
            "image_name": "scene_0032_038.jpg",
            "metrics": {
                "ADE_1s": 1.5157488824209155,
                "ADE_2s": 6.376990001236571,
                "ADE_3s": 12.296097461593318,
                "ADE_avg": 6.729612115083602,
                "FDE": 13.863941598922088,
                "missRate_2": 1.0
            },
            "inference": {
                "actions": "[(7.97, 0.038), (7.97, 0.025), (7.97, 0.011), (7.97, -0.003), (7.97, -0.017), (7.97, -0.030)]"
            }
        },
        {
            "frame_index": 40,
            "image_name": "scene_0032_040.jpg",
            "metrics": {
                "ADE_1s": 1.483958393831282,
                "ADE_2s": 4.234282807996683,
                "ADE_3s": 4.956207358018389,
                "ADE_avg": 3.5581495199487847,
                "FDE": 4.974642948617232,
                "missRate_2": 1.0
            },
            "inference": {
                "actions": "[(7.920, 0.063), (7.920, 0.063), (7.920, 0.063), (7.920, 0.063), (7.920, 0.063), (7.920, 0.063)]"
            }
        },
        {
            "frame_index": 42,
            "image_name": "scene_0032_042.jpg",
            "metrics": {
                "ADE_1s": 1.5566210672099128,
                "ADE_2s": 3.3298893033992307,
                "ADE_3s": 3.1927380567683175,
                "ADE_avg": 2.6930828091258205,
                "FDE": 3.4180088793422714,
                "missRate_2": 1.0
            },
            "inference": {
                "actions": "[(7.84, 0.072), (7.85, 0.075), (7.86, 0.078), (7.87, 0.081), (7.88, 0.084), (7.89, 0.087)]"
            }
        },
        {
            "frame_index": 44,
            "image_name": "scene_0032_044.jpg",
            "metrics": {
                "ADE_1s": 1.5312222992632007,
                "ADE_2s": 2.619801595218421,
                "ADE_3s": 3.708559245247251,
                "ADE_avg": 2.619861046576291,
                "FDE": 4.584632025701112,
                "missRate_2": 1.0
            },
            "inference": {
                "actions": "[(7.8, 0.077), (7.8, 0.077), (7.8, 0.077), (7.8, 0.077), (7.8, 0.077), (7.8, 0.077)]"
            }
        },
        {
            "frame_index": 46,
            "image_name": "scene_0032_046.jpg",
            "metrics": {
                "ADE_1s": 1.2442762079747833,
                "ADE_2s": 1.7317042160155018,
                "ADE_3s": 6.0676729878229265,
                "ADE_avg": 3.0145511372710705,
                "FDE": 7.661764657649979,
                "missRate_2": 1.0
            },
            "inference": {
                "actions": "[(7.87, 0.094), (7.87, 0.094), (7.87, 0.094), (7.87, 0.094), (7.87, 0.094), (7.87, 0.094)]"
            }
        },
        {
            "frame_index": 48,
            "image_name": "scene_0032_048.jpg",
            "metrics": {
                "ADE_1s": 1.007608810460548,
                "ADE_2s": 2.6690993240733696,
                "ADE_3s": 8.623849455129754,
                "ADE_avg": 4.100185863221224,
                "FDE": 10.396362358605678,
                "missRate_2": 1.0
            },
            "inference": {
                "actions": "[(7.974725952669619, 0.101), (7.989225952669619, 0.101), (8.003725952669619, 0.101), (8.018225952669619, 0.101), (8.032725952669619, 0.101), (8.047225952669619, 0.101)]"
            }
        }
    ],
    "scene_metrics": {
        "ADE_avg": 3.7084901511556136,
        "FDE": 8.890104329352667,
        "missRate_2": 0.92
    }
}