{
    "scene_info": {
        "name": "scene_0054"
    },
    "frames": [
        {
            "frame_index": 0,
            "image_name": "scene_0054_000.jpg",
            "metrics": {
                "ADE_1s": 0.8504556558871267,
                "ADE_2s": 2.990202216413943,
                "ADE_3s": 5.933739630364991,
                "ADE_avg": 3.258132500888687,
                "FDE": 6.5666354056924465,
                "missRate_2": 1.0
            },
            "inference": {
                "actions": "[(5.706616280939218, 0.0), (4.566616280939218, 0.0), (3.426616280939218, 0.0), (2.286616280939218, 0.0), (1.146616280939218, 0.0), (0.006616280939218, 0.0)]"
            }
        },
        {
            "frame_index": 2,
            "image_name": "scene_0054_002.jpg",
            "metrics": {
                "ADE_1s": 0.8174546135141642,
                "ADE_2s": 2.7774995179784687,
                "ADE_3s": 5.213766121380376,
                "ADE_avg": 2.936240084291003,
                "FDE": 5.566293601483159,
                "missRate_2": 1.0
            },
            "inference": {
                "actions": "[(5.559953, 0.0), (4.447962, 0.0), (3.335972, 0.0), (2.223981, 0.0), (1.111991, 0.0), (0.000000, 0.0)]"
            }
        },
        {
            "frame_index": 4,
            "image_name": "scene_0054_004.jpg",
            "metrics": {
                "ADE_1s": 0.9815944017031326,
                "ADE_2s": 3.2977477079419244,
                "ADE_3s": 5.670378838990803,
                "ADE_avg": 3.316573649545287,
                "FDE": 5.801025661743768,
                "missRate_2": 1.0
            },
            "inference": {
                "actions": "[(5.217417926694918, 0.0), (3.967417926694918, 0.0), (2.717417926694918, 0.0), (1.467417926694918, 0.0), (0.217417926694918, 0.0), (0.0, 0.0)]"
            }
        },
        {
            "frame_index": 6,
            "image_name": "scene_0054_006.jpg",
            "metrics": {
                "ADE_1s": 0.7638397661531633,
                "ADE_2s": 2.383021776384912,
                "ADE_3s": 3.440456559487644,
                "ADE_avg": 2.1957727006752394,
                "FDE": 3.454418812130316,
                "missRate_2": 1.0
            },
            "inference": {
                "actions": "[(5.235, 0.0), (4.190, 0.0), (3.145, 0.0), (2.100, 0.0), (1.055, 0.0), (0.010, 0.0)]"
            }
        },
        {
            "frame_index": 8,
            "image_name": "scene_0054_008.jpg",
            "metrics": {
                "ADE_1s": 0.6600869087017441,
                "ADE_2s": 2.0798821225461475,
                "ADE_3s": 2.4323783631091116,
                "ADE_avg": 1.7241157981190012,
                "FDE": 2.4330805964100253,
                "missRate_2": 1.0
            },
            "inference": {
                "actions": "[(5.10, 0.0), (4.08, 0.0), (3.06, 0.0), (2.04, 0.0), (1.02, 0.0), (0.00, 0.0)]"
            }
        },
        {
            "frame_index": 10,
            "image_name": "scene_0054_010.jpg",
            "metrics": {
                "ADE_1s": 0.5469552655402463,
                "ADE_2s": 1.6546089627207472,
                "ADE_3s": 1.420017634729433,
                "ADE_avg": 1.2071939543301422,
                "FDE": 1.420162723530055,
                "missRate_2": 0.0
            },
            "inference": {
                "actions": "[(4.97, 0.0), (3.98, 0.0), (2.98, 0.0), (1.99, 0.0), (0.99, 0.0), (0.00, 0.0)]"
            }
        },
        {
            "frame_index": 12,
            "image_name": "scene_0054_012.jpg",
            "metrics": {
                "ADE_1s": 0.4137034151928309,
                "ADE_2s": 1.0619607674659326,
                "ADE_3s": 0.4489466730420244,
                "ADE_avg": 0.6415369519002627,
                "FDE": 0.44895144032623946,
                "missRate_2": 0.0
            },
            "inference": {
                "actions": "[(4.83, 0.0), (3.87, 0.0), (2.90, 0.0), (1.93, 0.0), (0.97, 0.0), (0.00, 0.0)]"
            }
        },
        {
            "frame_index": 14,
            "image_name": "scene_0054_014.jpg",
            "metrics": {
                "ADE_1s": 0.2365858012734337,
                "ADE_2s": 0.34576067829238416,
                "ADE_3s": 0.5951171878251584,
                "ADE_avg": 0.3924878891303254,
                "FDE": 0.5951171878251584,
                "missRate_2": 0.0
            },
            "inference": {
                "actions": "[(4.76407, 0.0), (3.81125, 0.0), (2.85844, 0.0), (1.90563, 0.0), (0.95281, 0.0), (0.00000, 0.0)]"
            }
        },
        {
            "frame_index": 16,
            "image_name": "scene_0054_016.jpg",
            "metrics": {
                "ADE_1s": 0.5479075711583398,
                "ADE_2s": 0.38731628189003864,
                "ADE_3s": 0.5533319499195052,
                "ADE_avg": 0.49618526765596127,
                "FDE": 0.5533319499195052,
                "missRate_2": 0.0
            },
            "inference": {
                "actions": "[(4.037785093543821, 0.0), (3.2302280748350566, 0.0), (2.4226710561262923, 0.0), (1.615114037417528, 0.0), (0.8075570187087637, 0.0), (0.0, 0.0)]"
            }
        },
        {
            "frame_index": 18,
            "image_name": "scene_0054_018.jpg",
            "metrics": {
                "ADE_1s": 0.6080356174416744,
                "ADE_2s": 0.37097287637741855,
                "ADE_3s": 0.9920909415959854,
                "ADE_avg": 0.6570331451383594,
                "FDE": 0.9920909415959854,
                "missRate_2": 0.0
            },
            "inference": {
                "actions": "[(3.7167, 0.0), (2.9733, 0.0), (2.2300, 0.0), (1.4867, 0.0), (0.7433, 0.0), (0.0000, 0.0)]"
            }
        },
        {
            "frame_index": 20,
            "image_name": "scene_0054_020.jpg",
            "metrics": {
                "ADE_1s": 0.3196557865402392,
                "ADE_2s": 1.1586355721017405,
                "ADE_3s": 1.8981404778009126,
                "ADE_avg": 1.1254772788142973,
                "FDE": 1.8981404778009126,
                "missRate_2": 0.0
            },
            "inference": {
                "actions": "[(3.7362, 0.0), (2.9862, 0.0), (2.2362, 0.0), (1.4862, 0.0), (0.7362, 0.0), (0.0, 0.0)]"
            }
        },
        {
            "frame_index": 22,
            "image_name": "scene_0054_022.jpg",
            "metrics": {
                "ADE_1s": 0.43559532325103173,
                "ADE_2s": 2.3513786752882857,
                "ADE_3s": 3.139496696985387,
                "ADE_avg": 1.9754902318415681,
                "FDE": 3.139496696985387,
                "missRate_2": 1.0
            },
            "inference": {
                "actions": "[(3.9406139467910208, 0.0), (3.1524911574328166, 0.0), (2.3643683680746124, 0.0), (1.5762455787164082, 0.0), (0.788122789358204, 0.0), (0.0, 0.0)]"
            }
        },
        {
            "frame_index": 24,
            "image_name": "scene_0054_024.jpg",
            "metrics": {
                "ADE_1s": 0.9716006753239677,
                "ADE_2s": 3.1209957306453138,
                "ADE_3s": 3.8809957303443,
                "ADE_avg": 2.65786404543786,
                "FDE": 3.8809957303443,
                "missRate_2": 1.0
            },
            "inference": {
                "actions": "[(3.801, 0.0), (3.041, 0.0), (2.281, 0.0), (1.520, 0.0), (0.760, 0.0), (0.000, 0.0)]"
            }
        },
        {
            "frame_index": 26,
            "image_name": "scene_0054_026.jpg",
            "metrics": {
                "ADE_1s": 1.02037665668517,
                "ADE_2s": 2.7385728699104286,
                "ADE_3s": 3.316572869686724,
                "ADE_avg": 2.3585074654274405,
                "FDE": 3.316572869686724,
                "missRate_2": 1.0
            },
            "inference": {
                "actions": "[(2.891, 0.0), (2.313, 0.0), (1.735, 0.0), (1.156, 0.0), (0.578, 0.0), (0.000, 0.0)]"
            }
        },
        {
            "frame_index": 28,
            "image_name": "scene_0054_028.jpg",
            "metrics": {
                "ADE_1s": 0.10819546160391186,
                "ADE_2s": 0.10749322185251685,
                "ADE_3s": 0.10749322185251685,
                "ADE_avg": 0.10772730176964852,
                "FDE": 0.10749322185251685,
                "missRate_2": 0.0
            },
            "inference": {
                "actions": "[(1.125, 0.0), (0.0, 0.0), (0.0, 0.0), (0.0, 0.0), (0.0, 0.0), (0.0, 0.0)]"
            }
        },
        {
            "frame_index": 30,
            "image_name": "scene_0054_030.jpg",
            "metrics": {
                "ADE_1s": 0.12058945188196765,
                "ADE_2s": 0.12073453956562552,
                "ADE_3s": 0.12073453956562552,
                "ADE_avg": 0.12068617700440622,
                "FDE": 0.12073453956562552,
                "missRate_2": 0.0
            },
            "inference": {
                "actions": "[(0.005538756374592, 0.0), (0.0, 0.0), (0.0, 0.0), (0.0, 0.0), (0.0, 0.0), (0.0, 0.0)]"
            }
        },
        {
            "frame_index": 32,
            "image_name": "scene_0054_032.jpg",
            "metrics": {
                "ADE_1s": 1.2483277846142085,
                "ADE_2s": 4.995753186638814,
                "ADE_3s": 11.158007971202823,
                "ADE_avg": 5.800696314151949,
                "FDE": 12.975965584691165,
                "missRate_2": 1.0
            },
            "inference": {
                "actions": "[(1.250389, -0.011667), (2.500389, -0.023333), (3.750389, -0.035000), (5.000389, -0.046667), (6.250389, -0.058333), (7.500389, -0.070000)]"
            }
        },
        {
            "frame_index": 34,
            "image_name": "scene_0054_034.jpg",
            "metrics": {
                "ADE_1s": 0.000708284098057782,
                "ADE_2s": 0.000708284098057782,
                "ADE_3s": 0.000708284098057782,
                "ADE_avg": 0.000708284098057782,
                "FDE": 0.000708284098057782,
                "missRate_2": 0.0
            },
            "inference": {
                "actions": "[(0.0, 0.0), (0.0, 0.0), (0.0, 0.0), (0.0, 0.0), (0.0, 0.0), (0.0, 0.0)]"
            }
        },
        {
            "frame_index": 36,
            "image_name": "scene_0054_036.jpg",
            "metrics": {
                "ADE_1s": 9.1552734375e-05,
                "ADE_2s": 9.1552734375e-05,
                "ADE_3s": 9.1552734375e-05,
                "ADE_avg": 9.1552734375e-05,
                "FDE": 9.1552734375e-05,
                "missRate_2": 0.0
            },
            "inference": {
                "actions": "[(0.0, 0.0), (0.0, 0.0), (0.0, 0.0), (0.0, 0.0), (0.0, 0.0), (0.0, 0.0)]"
            }
        },
        {
            "frame_index": 38,
            "image_name": "scene_0054_038.jpg",
            "metrics": {
                "ADE_1s": 0.0,
                "ADE_2s": 0.0,
                "ADE_3s": 0.0,
                "ADE_avg": 0.0,
                "FDE": 0.0,
                "missRate_2": 0.0
            },
            "inference": {
                "actions": "[(0.0, 0.0), (0.0, 0.0), (0.0, 0.0), (0.0, 0.0), (0.0, 0.0), (0.0, 0.0)]"
            }
        },
        {
            "frame_index": 40,
            "image_name": "scene_0054_040.jpg",
            "metrics": {
                "ADE_1s": 0.8349987871195977,
                "ADE_2s": 3.338337873581408,
                "ADE_3s": 7.464694216316658,
                "ADE_avg": 3.879343625672554,
                "FDE": 8.688327207552017,
                "missRate_2": 1.0
            },
            "inference": {
                "actions": "[(0.835, -0.01), (1.67, -0.03), (2.505, -0.05), (3.34, -0.07), (4.175, -0.07), (5.01, -0.07)]"
            }
        },
        {
            "frame_index": 42,
            "image_name": "scene_0054_042.jpg",
            "metrics": {
                "ADE_1s": 0.0,
                "ADE_2s": 0.0,
                "ADE_3s": 0.0,
                "ADE_avg": 0.0,
                "FDE": 0.0,
                "missRate_2": 0.0
            },
            "inference": {
                "actions": "[(0.0, 0.0), (0.0, 0.0), (0.0, 0.0), (0.0, 0.0), (0.0, 0.0), (0.0, 0.0)]"
            }
        },
        {
            "frame_index": 44,
            "image_name": "scene_0054_044.jpg",
            "metrics": {
                "ADE_1s": 0.0,
                "ADE_2s": 0.0,
                "ADE_3s": 0.0,
                "ADE_avg": 0.0,
                "FDE": 0.0,
                "missRate_2": 0.0
            },
            "inference": {
                "actions": "[(0.0, 0), (0.0, 0), (0.0, 0), (0.0, 0), (0.0, 0), (0.0, 0)]"
            }
        },
        {
            "frame_index": 46,
            "image_name": "scene_0054_046.jpg",
            "metrics": {
                "ADE_1s": 1.124944197555568,
                "ADE_2s": 4.942886853035334,
                "ADE_3s": 9.750077406124726,
                "ADE_avg": 5.272636152238543,
                "FDE": 10.888936280114585,
                "missRate_2": 1.0
            },
            "inference": {
                "actions": "[(1.0, -0.05), (2.5, -0.10), (4.0, -0.15), (5.0, -0.18), (5.8, -0.16), (6.5, -0.12)]"
            }
        },
        {
            "frame_index": 48,
            "image_name": "scene_0054_048.jpg",
            "metrics": {
                "ADE_1s": 0.0,
                "ADE_2s": 0.0,
                "ADE_3s": 0.0,
                "ADE_avg": 0.0,
                "FDE": 0.0,
                "missRate_2": 0.0
            },
            "inference": {
                "actions": "[(0.0, 0.0), (0.0, 0.0), (0.0, 0.0), (0.0, 0.0), (0.0, 0.0), (0.0, 0.0)]"
            }
        }
    ],
    "scene_metrics": {
        "ADE_avg": 1.6049800148345985,
        "FDE": 2.9139428306432933,
        "missRate_2": 0.44
    }
}