{
    "scene_info": {
        "name": "scene_0008"
    },
    "frames": [
        {
            "frame_index": 0,
            "image_name": "scene_0008_000.jpg",
            "metrics": {
                "ADE_1s": 0.4827463351436672,
                "ADE_2s": 2.7668361013460903,
                "ADE_3s": 3.609898233764154,
                "ADE_avg": 2.286493556751304,
                "FDE": 3.5044477958407754,
                "missRate_2": 1.0
            },
            "inference": {
                "actions": "[(4.746, 0.001), (3.797, 0.002), (2.847, 0.003), (1.898, 0.004), (0.949, 0.005), (0.000, 0.005)]"
            }
        },
        {
            "frame_index": 2,
            "image_name": "scene_0008_002.jpg",
            "metrics": {
                "ADE_1s": 0.9793690195633051,
                "ADE_2s": 3.4224260221915475,
                "ADE_3s": 4.074437668805956,
                "ADE_avg": 2.8254109035202695,
                "FDE": 3.8678541351222697,
                "missRate_2": 1.0
            },
            "inference": {
                "actions": "[(4.3869, 0.005), (3.5119, 0.010), (2.6369, 0.015), (1.7619, 0.020), (0.8869, 0.025), (0.0119, 0.030)]"
            }
        },
        {
            "frame_index": 4,
            "image_name": "scene_0008_004.jpg",
            "metrics": {
                "ADE_1s": 1.2070270020871863,
                "ADE_2s": 3.3025685669975866,
                "ADE_3s": 3.5793154725300416,
                "ADE_avg": 2.6963036805382714,
                "FDE": 3.26780109368198,
                "missRate_2": 1.0
            },
            "inference": {
                "actions": "[(3.5639, 0.005), (2.8511, 0.015), (2.1383, 0.025), (1.4256, 0.025), (0.7128, 0.025), (0.0000, 0.025)]"
            }
        },
        {
            "frame_index": 6,
            "image_name": "scene_0008_006.jpg",
            "metrics": {
                "ADE_1s": 0.7834605164748413,
                "ADE_2s": 1.4948521803181343,
                "ADE_3s": 0.7851999435023335,
                "ADE_avg": 1.0211708800984363,
                "FDE": 0.3865499267211219,
                "missRate_2": 0.0
            },
            "inference": {
                "actions": "[(2.116, 0.0), (1.416, 0.0), (0.716, 0.0), (0.016, 0.0), (0.000, 0.0), (0.000, 0.0)]"
            }
        },
        {
            "frame_index": 8,
            "image_name": "scene_0008_008.jpg",
            "metrics": {
                "ADE_1s": 0.6804860135374206,
                "ADE_2s": 1.410464677488235,
                "ADE_3s": 0.6266196875809438,
                "ADE_avg": 0.9058567928688664,
                "FDE": 0.14679722874813303,
                "missRate_2": 0.0
            },
            "inference": {
                "actions": "[(1.267, -0.01), (1.014, -0.01), (0.760, -0.01), (0.507, -0.01), (0.253, -0.01), (0.000, -0.01)]"
            }
        },
        {
            "frame_index": 10,
            "image_name": "scene_0008_010.jpg",
            "metrics": {
                "ADE_1s": 0.2874750439773594,
                "ADE_2s": 0.43654861179867355,
                "ADE_3s": 0.8558324764396706,
                "ADE_avg": 0.5266187107385679,
                "FDE": 1.4155092917928007,
                "missRate_2": 0.0
            },
            "inference": {
                "actions": "[(0.425, 0.0), (0.34, 0.0), (0.255, 0.0), (0.17, 0.0), (0.085, 0.0), (0.0, 0.0)]"
            }
        },
        {
            "frame_index": 12,
            "image_name": "scene_0008_012.jpg",
            "metrics": {
                "ADE_1s": 0.001190185546875,
                "ADE_2s": 0.23571778289399026,
                "ADE_3s": 1.9653627554071933,
                "ADE_avg": 0.7340902412826861,
                "FDE": 2.6056522672211946,
                "missRate_2": 1.0
            },
            "inference": {
                "actions": "[(0.0, 0.0), (0.0, 0.0), (0.0, 0.0), (0.0, 0.0), (0.0, 0.0), (0.0, 0.0)]"
            }
        },
        {
            "frame_index": 14,
            "image_name": "scene_0008_014.jpg",
            "metrics": {
                "ADE_1s": 0.000274658203125,
                "ADE_2s": 0.4358367923036676,
                "ADE_3s": 2.5115360491266387,
                "ADE_avg": 0.9825491665444771,
                "FDE": 3.2356270087919596,
                "missRate_2": 1.0
            },
            "inference": {
                "actions": "[(0.0, 0.154), (0.0, 0.154), (0.0, 0.154), (0.0, 0.154), (0.0, 0.154), (0.0, 0.154)]"
            }
        },
        {
            "frame_index": 16,
            "image_name": "scene_0008_016.jpg",
            "metrics": {
                "ADE_1s": 0.0036011065465478215,
                "ADE_2s": 0.7172546402372488,
                "ADE_3s": 3.1273048032587076,
                "ADE_avg": 1.2827201833475013,
                "FDE": 3.9393322605293037,
                "missRate_2": 1.0
            },
            "inference": {
                "actions": "[(0.0, 0.0), (0.0, 0.0), (0.0, 0.0), (0.0, 0.0), (0.0, 0.0), (0.0, 0.0)]"
            }
        },
        {
            "frame_index": 18,
            "image_name": "scene_0008_018.jpg",
            "metrics": {
                "ADE_1s": 0.029953002929687497,
                "ADE_2s": 1.0674133310763954,
                "ADE_3s": 3.815751202744436,
                "ADE_avg": 1.6377058455835065,
                "FDE": 4.720491068069809,
                "missRate_2": 1.0
            },
            "inference": {
                "actions": "[(0.0, 0.0), (0.0, 0.0), (0.0, 0.0), (0.0, 0.0), (0.0, 0.0), (0.0, 0.0)]"
            }
        },
        {
            "frame_index": 20,
            "image_name": "scene_0008_020.jpg",
            "metrics": {
                "ADE_1s": 0.10588073730468749,
                "ADE_2s": 1.4832611589106477,
                "ADE_3s": 4.580461062181194,
                "ADE_avg": 2.0565343194655097,
                "FDE": 5.5829487043971415,
                "missRate_2": 1.0
            },
            "inference": {
                "actions": "[(0.0, 0.0), (0.0, 0.0), (0.0, 0.0), (0.0, 0.0), (0.0, 0.0), (0.0, 0.0)]"
            }
        },
        {
            "frame_index": 22,
            "image_name": "scene_0008_022.jpg",
            "metrics": {
                "ADE_1s": 0.23452759777601861,
                "ADE_2s": 1.9641725699550312,
                "ADE_3s": 5.4096269131937165,
                "ADE_avg": 2.536109026974922,
                "FDE": 6.499245101306913,
                "missRate_2": 1.0
            },
            "inference": {
                "actions": "[(0.0, 0.0), (0.0, 0.0), (0.0, 0.0), (0.0, 0.0), (0.0, 0.0), (0.0, 0.0)]"
            }
        },
        {
            "frame_index": 24,
            "image_name": "scene_0008_024.jpg",
            "metrics": {
                "ADE_1s": 0.5665383122780561,
                "ADE_2s": 1.4936398767091725,
                "ADE_3s": 2.7497374656238733,
                "ADE_avg": 1.6033052182037009,
                "FDE": 3.133803068900176,
                "missRate_2": 1.0
            },
            "inference": {
                "actions": "[(1.0028, 0.0), (2.0028, 0.0), (3.0028, 0.0), (4.0028, 0.0), (5.0028, 0.0), (6.0028, 0.0)]"
            }
        },
        {
            "frame_index": 26,
            "image_name": "scene_0008_026.jpg",
            "metrics": {
                "ADE_1s": 0.3923895928923733,
                "ADE_2s": 1.118927390723567,
                "ADE_3s": 2.263404051748222,
                "ADE_avg": 1.2582403451213873,
                "FDE": 2.7183611790392823,
                "missRate_2": 1.0
            },
            "inference": {
                "actions": "[(1.1365880365227643, 0), (2.1365880365227643, 0), (3.1365880365227643, 0), (4.1365880365227643, 0), (5.1365880365227643, 0), (6.1365880365227643, 0)]"
            }
        },
        {
            "frame_index": 28,
            "image_name": "scene_0008_028.jpg",
            "metrics": {
                "ADE_1s": 0.601744163831164,
                "ADE_2s": 2.082405415497306,
                "ADE_3s": 4.643674495119,
                "ADE_avg": 2.4426080248158235,
                "FDE": 5.600809500938777,
                "missRate_2": 1.0
            },
            "inference": {
                "actions": "[(1.729, 0), (2.979, 0), (4.229, 0), (5.479, 0), (6.729, 0), (7.979, 0)]"
            }
        },
        {
            "frame_index": 30,
            "image_name": "scene_0008_030.jpg",
            "metrics": {
                "ADE_1s": 0.05338130778552027,
                "ADE_2s": 0.28268035995668095,
                "ADE_3s": 0.6954295888532813,
                "ADE_avg": 0.34383041886516086,
                "FDE": 0.6855739382608078,
                "missRate_2": 0.0
            },
            "inference": {
                "actions": "[(1.567, 0.005), (2.167, 0.010), (2.767, 0.015), (3.367, 0.018), (3.967, 0.020), (4.567, 0.020)]"
            }
        },
        {
            "frame_index": 32,
            "image_name": "scene_0008_032.jpg",
            "metrics": {
                "ADE_1s": 0.4820176186898516,
                "ADE_2s": 1.3799260753801765,
                "ADE_3s": 3.70981427438495,
                "ADE_avg": 1.8572526561516594,
                "FDE": 4.646796709008161,
                "missRate_2": 1.0
            },
            "inference": {
                "actions": "[(2.336, -0.002), (3.336, 0.015), (4.336, 0.031), (5.336, 0.047), (6.336, 0.064), (7.336, 0.080)]"
            }
        },
        {
            "frame_index": 34,
            "image_name": "scene_0008_034.jpg",
            "metrics": {
                "ADE_1s": 0.24239820231306541,
                "ADE_2s": 0.48490699351171207,
                "ADE_3s": 2.1698163233433356,
                "ADE_avg": 0.9657071730560376,
                "FDE": 2.900155540970558,
                "missRate_2": 1.0
            },
            "inference": {
                "actions": "[(2.425, 0.009), (3.175, 0.021), (3.925, 0.033), (4.675, 0.045), (5.425, 0.057), (6.175, 0.069)]"
            }
        },
        {
            "frame_index": 36,
            "image_name": "scene_0008_036.jpg",
            "metrics": {
                "ADE_1s": 0.23410080087272833,
                "ADE_2s": 0.4861676183346531,
                "ADE_3s": 1.9841044852450236,
                "ADE_avg": 0.9014576348174682,
                "FDE": 2.4966355012830053,
                "missRate_2": 1.0
            },
            "inference": {
                "actions": "[(2.744, 0.0), (3.494, 0.0), (4.244, 0.0), (4.994, 0.0), (5.744, 0.0), (6.494, 0.0)]"
            }
        },
        {
            "frame_index": 38,
            "image_name": "scene_0008_038.jpg",
            "metrics": {
                "ADE_1s": 0.21282643796724635,
                "ADE_2s": 0.6034774241841241,
                "ADE_3s": 2.358219251975144,
                "ADE_avg": 1.0581743713755047,
                "FDE": 2.8896255305324483,
                "missRate_2": 1.0
            },
            "inference": {
                "actions": "[(3.058, 0.0), (3.808, 0.0), (4.558, 0.0), (5.308, 0.0), (6.058, 0.0), (6.808, 0.0)]"
            }
        },
        {
            "frame_index": 40,
            "image_name": "scene_0008_040.jpg",
            "metrics": {
                "ADE_1s": 0.2307283046622055,
                "ADE_2s": 1.0137712041140365,
                "ADE_3s": 3.1948366490522915,
                "ADE_avg": 1.4797787192761778,
                "FDE": 3.8234576798481448,
                "missRate_2": 1.0
            },
            "inference": {
                "actions": "[(3.426, 0.0), (4.221, 0.0), (5.016, 0.0), (5.811, 0.0), (6.606, 0.0), (7.401, 0.0)]"
            }
        },
        {
            "frame_index": 42,
            "image_name": "scene_0008_042.jpg",
            "metrics": {
                "ADE_1s": 0.09739421080262287,
                "ADE_2s": 0.2061273210506466,
                "ADE_3s": 1.4217490391976058,
                "ADE_avg": 0.5750901903502917,
                "FDE": 1.996758941673691,
                "missRate_2": 0.0
            },
            "inference": {
                "actions": "[(3.4694, -0.004), (3.9694, -0.004), (4.4694, -0.004), (4.9694, -0.004), (5.4694, -0.004), (5.9694, -0.004)]"
            }
        },
        {
            "frame_index": 44,
            "image_name": "scene_0008_044.jpg",
            "metrics": {
                "ADE_1s": 0.3208986612199226,
                "ADE_2s": 1.9542243340124545,
                "ADE_3s": 5.053913199194005,
                "ADE_avg": 2.443012064808794,
                "FDE": 6.1754222209096525,
                "missRate_2": 1.0
            },
            "inference": {
                "actions": "[(4.174538055860846, 0.0), (5.024538055860846, 0.0), (5.874538055860846, 0.0), (6.724538055860846, 0.0), (7.574538055860846, 0.0), (8.424538055860846, 0.0)]"
            }
        },
        {
            "frame_index": 46,
            "image_name": "scene_0008_046.jpg",
            "metrics": {
                "ADE_1s": 0.4945473506868815,
                "ADE_2s": 2.642670691986779,
                "ADE_3s": 6.6131233959802795,
                "ADE_avg": 3.250113812884646,
                "FDE": 8.259332673904389,
                "missRate_2": 1.0
            },
            "inference": {
                "actions": "[(4.599302801362921, 0.0), (5.499302801362921, 0.0), (6.399302801362921, 0.0), (7.299302801362921, 0.0), (8.199302801362921, 0.0), (9.099302801362921, 0.0)]"
            }
        },
        {
            "frame_index": 48,
            "image_name": "scene_0008_048.jpg",
            "metrics": {
                "ADE_1s": 0.7587199932866999,
                "ADE_2s": 3.3826444789387597,
                "ADE_3s": 8.581146358810702,
                "ADE_avg": 4.240836943678722,
                "FDE": 10.860966020583845,
                "missRate_2": 1.0
            },
            "inference": {
                "actions": "[(5.045220616094656, 0.0), (5.995220616094656, 0.0), (6.945220616094656, 0.0), (7.895220616094656, 0.0), (8.845220616094656, 0.0), (9.795220616094656, 0.0)]"
            }
        }
    ],
    "scene_metrics": {
        "ADE_avg": 1.6764388352447874,
        "FDE": 3.814398175523053,
        "missRate_2": 0.8
    }
}